MANIFEST.in
README.rst
base.cfg
setup.py
test-4.2.x.cfg
Products/__init__.py
Products.csvreplicata.egg-info/PKG-INFO
Products.csvreplicata.egg-info/SOURCES.txt
Products.csvreplicata.egg-info/dependency_links.txt
Products.csvreplicata.egg-info/entry_points.txt
Products.csvreplicata.egg-info/namespace_packages.txt
Products.csvreplicata.egg-info/not-zip-safe
Products.csvreplicata.egg-info/requires.txt
Products.csvreplicata.egg-info/top_level.txt
Products/csvreplicata/AppConfig.py
Products/csvreplicata/__init__.py
Products/csvreplicata/adapters.py
Products/csvreplicata/app_config.py
Products/csvreplicata/config.py
Products/csvreplicata/configure.zcml
Products/csvreplicata/contributors.txt
Products/csvreplicata/csvreplicataTool.py
Products/csvreplicata/exceptions.py
Products/csvreplicata/exportimport_plugins.py
Products/csvreplicata/interfaces.py
Products/csvreplicata/meta.zcml
Products/csvreplicata/profiles.zcml
Products/csvreplicata/replicator.py
Products/csvreplicata/setuphandlers.py
Products/csvreplicata/tool.gif
Products/csvreplicata/version.txt
Products/csvreplicata/Extensions/Install.py
Products/csvreplicata/Extensions/__init__.py
Products/csvreplicata/browser/__init__.py
Products/csvreplicata/browser/configure.zcml
Products/csvreplicata/browser/manage.pt
Products/csvreplicata/browser/manager.py
Products/csvreplicata/handlers/__init__.py
Products/csvreplicata/handlers/base.py
Products/csvreplicata/handlers/file.py
Products/csvreplicata/handlers/maps.py
Products/csvreplicata/handlers/reference.py
Products/csvreplicata/profiles/default/actionicons.xml
Products/csvreplicata/profiles/default/actions.xml
Products/csvreplicata/profiles/default/controlpanel.xml
Products/csvreplicata/profiles/default/cssregistry.xml
Products/csvreplicata/profiles/default/csvreplicata_marker.txt
Products/csvreplicata/profiles/default/import_steps.xml
Products/csvreplicata/profiles/default/jsregistry.xml
Products/csvreplicata/profiles/default/metadata.xml
Products/csvreplicata/profiles/default/propertiestool.xml
Products/csvreplicata/profiles/default/skins.xml
Products/csvreplicata/profiles/default/toolset.xml
Products/csvreplicata/profiles/default/types.xml
Products/csvreplicata/profiles/default/types/csvreplicataTool.xml
Products/csvreplicata/skins/csvreplicata_images/csvreplicataTool.gif
