Metadata-Version: 1.1
Name: Products.csvreplicata
Version: 1.1.13
Summary: CSV import/export for Archetypes or other contents (via plugins for the later). Created by Makina Corpus.
Home-page: https://svn.plone.org/svn/collective/Products.csvreplicata
Author: Eric BREHAULT
Author-email: eric.brehault@makina-corpus.org
License: GPL
Keywords: archetypes,import/export,csv,replication,synchronisation
Platform: UNKNOWN
Classifier: Framework :: Plone
Classifier: Programming Language :: Python
Classifier: Topic :: Software Development :: Libraries :: Python Modules
